{"cameraMode":{"drawMode":0,"name":"Shaded","section":"Shading Mode"},"sceneLighting":true,"audioPlay":false,"sceneViewState":{"m_AlwaysRefresh":false,"showFog":true,"showSkybox":true,"showFlares":true,"showImageEffects":true,"showParticleSystems":true,"showVisualEffectGraphs":true,"m_FxEnabled":true},"in2DMode":false,"pivot":{"x":-5.314527988433838,"y":56.515621185302737,"z":148.0455322265625},"rotation":{"x":0.18297839164733888,"y":-0.1874789595603943,"z":0.03557237610220909,"w":0.9644272923469544},"size":95.22352600097656,"orthographic":false}